{
  "annotations": {
    "list": [
      {
        "builtIn": 1,
        "datasource": "-- Grafana --",
        "enable": true,
        "hide": true,
        "iconColor": "rgba(0, 211, 255, 1)",
        "name": "Annotations & Alerts",
        "target": {
          "limit": 100,
          "matchAny": false,
          "tags": [],
          "type": "dashboard"
        },
        "type": "dashboard"
      }
    ]
  },
  "editable": true,
  "fiscalYearStartMonth": 0,
  "graphTooltip": 0,
  "id": 42,
  "iteration": 1645272643173,
  "links": [],
  "liveNow": false,
  "panels": [
    {
      "collapsed": false,
      "gridPos": {
        "h": 1,
        "w": 24,
        "x": 0,
        "y": 0
      },
      "id": 18,
      "panels": [],
      "title": "HTTP",
      "type": "row"
    },
    {
      "datasource": {
        "type": "prometheus",
        "uid": "P1809F7CD0C75ACF3"
      },
      "description": "The RPS data by handler",
      "fieldConfig": {
        "defaults": {
          "custom": {
            "align": "left",
            "displayMode": "auto"
          },
          "mappings": [],
          "thresholds": {
            "mode": "absolute",
            "steps": [
              {
                "color": "green",
                "value": null
              }
            ]
          }
        },
        "overrides": [
          {
            "matcher": {
              "id": "byName",
              "options": "Value"
            },
            "properties": [
              {
                "id": "unit",
                "value": "reqps"
              },
              {
                "id": "displayName",
                "value": "Reqps"
              }
            ]
          }
        ]
      },
      "gridPos": {
        "h": 5,
        "w": 12,
        "x": 0,
        "y": 1
      },
      "id": 43,
      "options": {
        "footer": {
          "fields": "",
          "reducer": [
            "sum"
          ],
          "show": false
        },
        "showHeader": true
      },
      "pluginVersion": "8.3.5",
      "targets": [
        {
          "expr": "sum(rate(http_request_duration_seconds_count{service=\"rollify-server\"}[${interval}])) by (handler, method, code) > 0",
          "format": "table",
          "instant": true,
          "interval": "",
          "legendFormat": "",
          "refId": "A"
        }
      ],
      "title": "HTTP RPS by handler",
      "transformations": [
        {
          "id": "filterFieldsByName",
          "options": {
            "include": {
              "names": [
                "code",
                "handler",
                "Value",
                "method"
              ]
            }
          }
        }
      ],
      "type": "table"
    },
    {
      "datasource": {
        "type": "prometheus",
        "uid": "P1809F7CD0C75ACF3"
      },
      "description": "The HTTP latency data by handler",
      "fieldConfig": {
        "defaults": {
          "custom": {
            "align": "left",
            "displayMode": "auto"
          },
          "mappings": [],
          "thresholds": {
            "mode": "absolute",
            "steps": [
              {
                "color": "green",
                "value": null
              }
            ]
          }
        },
        "overrides": [
          {
            "matcher": {
              "id": "byName",
              "options": "Value"
            },
            "properties": [
              {
                "id": "unit",
                "value": "ms"
              },
              {
                "id": "displayName",
                "value": "Latency"
              },
              {
                "id": "thresholds",
                "value": {
                  "mode": "absolute",
                  "steps": [
                    {
                      "color": "green",
                      "value": null
                    },
                    {
                      "color": "orange",
                      "value": 500
                    },
                    {
                      "color": "red",
                      "value": 1000
                    }
                  ]
                }
              },
              {
                "id": "custom.displayMode",
                "value": "color-text"
              }
            ]
          }
        ]
      },
      "gridPos": {
        "h": 5,
        "w": 12,
        "x": 12,
        "y": 1
      },
      "id": 44,
      "options": {
        "footer": {
          "fields": "",
          "reducer": [
            "sum"
          ],
          "show": false
        },
        "showHeader": true
      },
      "pluginVersion": "8.3.5",
      "targets": [
        {
          "expr": "(histogram_quantile(0.99, sum(rate(http_request_duration_seconds_bucket{service=\"rollify-server\"}[${interval}])) by (le, handler, method)) > 0) * 1000",
          "format": "table",
          "instant": true,
          "interval": "",
          "legendFormat": "",
          "refId": "A"
        }
      ],
      "title": "HTTP latency by handler",
      "transformations": [
        {
          "id": "filterFieldsByName",
          "options": {
            "include": {
              "names": [
                "handler",
                "Value",
                "method"
              ]
            }
          }
        }
      ],
      "type": "table"
    },
    {
      "aliasColors": {},
      "bars": false,
      "dashLength": 10,
      "dashes": false,
      "datasource": {
        "type": "prometheus",
        "uid": "P1809F7CD0C75ACF3"
      },
      "description": "HTTP API request rate",
      "fieldConfig": {
        "defaults": {
          "links": []
        },
        "overrides": []
      },
      "fill": 1,
      "fillGradient": 2,
      "gridPos": {
        "h": 8,
        "w": 12,
        "x": 0,
        "y": 6
      },
      "hiddenSeries": false,
      "id": 25,
      "legend": {
        "avg": false,
        "current": false,
        "max": false,
        "min": false,
        "show": true,
        "total": false,
        "values": false
      },
      "lines": true,
      "linewidth": 1,
      "nullPointMode": "null",
      "options": {
        "alertThreshold": true
      },
      "percentage": false,
      "pluginVersion": "8.3.5",
      "pointradius": 2,
      "points": false,
      "renderer": "flot",
      "seriesOverrides": [
        {
          "$$hashKey": "object:185",
          "alias": "error %",
          "color": "#F2495C",
          "stack": "B",
          "yaxis": 2
        }
      ],
      "spaceLength": 10,
      "stack": true,
      "steppedLine": false,
      "targets": [
        {
          "expr": "sum(rate(http_request_duration_seconds_count{service=\"rollify-server\"}[${interval}])) by (code)",
          "interval": "",
          "legendFormat": "{{code}}",
          "refId": "A"
        },
        {
          "expr": "sum(rate(http_request_duration_seconds_count{service=\"rollify-server\", code=~\"5..|429\"}[${interval}]))\n/\nsum(rate(http_request_duration_seconds_count{service=\"rollify-server\"}[${interval}]))",
          "interval": "",
          "legendFormat": "error %",
          "refId": "B"
        }
      ],
      "thresholds": [],
      "timeRegions": [],
      "title": "HTTP request rate",
      "tooltip": {
        "shared": true,
        "sort": 0,
        "value_type": "individual"
      },
      "type": "graph",
      "xaxis": {
        "mode": "time",
        "show": true,
        "values": []
      },
      "yaxes": [
        {
          "$$hashKey": "object:115",
          "format": "reqps",
          "logBase": 1,
          "show": true
        },
        {
          "$$hashKey": "object:116",
          "format": "percentunit",
          "logBase": 1,
          "max": "1",
          "min": "0",
          "show": true
        }
      ],
      "yaxis": {
        "align": false
      }
    },
    {
      "aliasColors": {},
      "bars": false,
      "dashLength": 10,
      "dashes": false,
      "datasource": {
        "type": "prometheus",
        "uid": "P1809F7CD0C75ACF3"
      },
      "description": "HTTP API request latency",
      "fieldConfig": {
        "defaults": {
          "links": []
        },
        "overrides": []
      },
      "fill": 1,
      "fillGradient": 2,
      "gridPos": {
        "h": 8,
        "w": 12,
        "x": 12,
        "y": 6
      },
      "hiddenSeries": false,
      "id": 31,
      "legend": {
        "avg": false,
        "current": false,
        "max": false,
        "min": false,
        "show": true,
        "total": false,
        "values": false
      },
      "lines": true,
      "linewidth": 1,
      "nullPointMode": "null",
      "options": {
        "alertThreshold": true
      },
      "percentage": false,
      "pluginVersion": "8.3.5",
      "pointradius": 2,
      "points": false,
      "renderer": "flot",
      "seriesOverrides": [
        {
          "$$hashKey": "object:185",
          "alias": "p99",
          "color": "#FA6400"
        },
        {
          "$$hashKey": "object:303",
          "alias": "p90",
          "color": "#FFB357"
        },
        {
          "$$hashKey": "object:311",
          "alias": "p50",
          "color": "#FFCB7D"
        }
      ],
      "spaceLength": 10,
      "stack": false,
      "steppedLine": false,
      "targets": [
        {
          "expr": "histogram_quantile(0.99, sum(rate(http_request_duration_seconds_bucket{service=\"rollify-server\",handler!~\".*/ws/.*\"}[${interval}])) by (le))",
          "interval": "",
          "legendFormat": "p99",
          "refId": "A"
        },
        {
          "expr": "histogram_quantile(0.90, sum(rate(http_request_duration_seconds_bucket{service=\"rollify-server\",handler!~\".*/ws/.*\"}[${interval}])) by (le))",
          "interval": "",
          "legendFormat": "p90",
          "refId": "B"
        },
        {
          "expr": "histogram_quantile(0.50, sum(rate(http_request_duration_seconds_bucket{service=\"rollify-server\",handler!~\".*/ws/.*\"}[${interval}])) by (le))",
          "interval": "",
          "legendFormat": "p50",
          "refId": "C"
        }
      ],
      "thresholds": [],
      "timeRegions": [],
      "title": "HTTP request latency",
      "tooltip": {
        "shared": true,
        "sort": 0,
        "value_type": "individual"
      },
      "type": "graph",
      "xaxis": {
        "mode": "time",
        "show": true,
        "values": []
      },
      "yaxes": [
        {
          "$$hashKey": "object:115",
          "format": "s",
          "logBase": 1,
          "show": true
        },
        {
          "$$hashKey": "object:116",
          "format": "short",
          "logBase": 1,
          "show": true
        }
      ],
      "yaxis": {
        "align": false
      }
    },
    {
      "collapsed": false,
      "gridPos": {
        "h": 1,
        "w": 24,
        "x": 0,
        "y": 14
      },
      "id": 51,
      "panels": [],
      "title": "Events and Websockets",
      "type": "row"
    },
    {
      "aliasColors": {},
      "bars": false,
      "dashLength": 10,
      "dashes": false,
      "datasource": {
        "type": "prometheus",
        "uid": "P1809F7CD0C75ACF3"
      },
      "description": "The number of current connected subscribers",
      "fieldConfig": {
        "defaults": {
          "links": []
        },
        "overrides": []
      },
      "fill": 1,
      "fillGradient": 4,
      "gridPos": {
        "h": 7,
        "w": 17,
        "x": 0,
        "y": 15
      },
      "hiddenSeries": false,
      "id": 64,
      "legend": {
        "avg": false,
        "current": false,
        "max": false,
        "min": false,
        "show": true,
        "total": false,
        "values": false
      },
      "lines": true,
      "linewidth": 1,
      "nullPointMode": "null",
      "options": {
        "alertThreshold": true
      },
      "percentage": false,
      "pluginVersion": "8.3.5",
      "pointradius": 2,
      "points": false,
      "renderer": "flot",
      "seriesOverrides": [
        {
          "$$hashKey": "object:185",
          "alias": "error %",
          "color": "#F2495C",
          "stack": "B",
          "yaxis": 2
        }
      ],
      "spaceLength": 10,
      "stack": true,
      "steppedLine": false,
      "targets": [
        {
          "expr": "sum(rollify_subscriber_subscribers_subscribed{service=\"rollify-server\"}) by (subscription)",
          "interval": "",
          "legendFormat": "{{subscription}}",
          "refId": "A"
        }
      ],
      "thresholds": [],
      "timeRegions": [],
      "title": "Number of subscriptions (Subscribers)",
      "tooltip": {
        "shared": true,
        "sort": 0,
        "value_type": "individual"
      },
      "type": "graph",
      "xaxis": {
        "mode": "time",
        "show": true,
        "values": []
      },
      "yaxes": [
        {
          "$$hashKey": "object:115",
          "decimals": 0,
          "format": "short",
          "logBase": 1,
          "show": true
        },
        {
          "$$hashKey": "object:116",
          "format": "percentunit",
          "logBase": 1,
          "max": "1",
          "min": "0",
          "show": false
        }
      ],
      "yaxis": {
        "align": false
      }
    },
    {
      "datasource": {
        "type": "prometheus",
        "uid": "P1809F7CD0C75ACF3"
      },
      "description": "The number of subscriptions per instance",
      "fieldConfig": {
        "defaults": {
          "links": [],
          "mappings": [],
          "thresholds": {
            "mode": "absolute",
            "steps": [
              {
                "color": "blue",
                "value": null
              }
            ]
          }
        },
        "overrides": []
      },
      "gridPos": {
        "h": 7,
        "w": 7,
        "x": 17,
        "y": 15
      },
      "id": 65,
      "options": {
        "displayMode": "gradient",
        "orientation": "horizontal",
        "reduceOptions": {
          "calcs": [
            "last"
          ],
          "fields": "",
          "values": false
        },
        "showUnfilled": true
      },
      "pluginVersion": "8.3.5",
      "targets": [
        {
          "expr": "sum(rollify_subscriber_subscribers_subscribed{service=\"rollify-server\"}) by (instance)",
          "interval": "",
          "legendFormat": "{{instance}}",
          "refId": "A"
        }
      ],
      "title": "Subscriptions per instance",
      "type": "bargauge"
    },
    {
      "aliasColors": {},
      "bars": false,
      "dashLength": 10,
      "dashes": false,
      "datasource": {
        "type": "prometheus",
        "uid": "P1809F7CD0C75ACF3"
      },
      "description": "The rate of events published",
      "fieldConfig": {
        "defaults": {
          "links": []
        },
        "overrides": []
      },
      "fill": 1,
      "fillGradient": 2,
      "gridPos": {
        "h": 8,
        "w": 12,
        "x": 0,
        "y": 22
      },
      "hiddenSeries": false,
      "id": 57,
      "legend": {
        "avg": false,
        "current": false,
        "max": false,
        "min": false,
        "show": true,
        "total": false,
        "values": false
      },
      "lines": true,
      "linewidth": 1,
      "nullPointMode": "null",
      "options": {
        "alertThreshold": true
      },
      "percentage": false,
      "pluginVersion": "8.3.5",
      "pointradius": 2,
      "points": false,
      "renderer": "flot",
      "seriesOverrides": [
        {
          "$$hashKey": "object:185",
          "alias": "error %",
          "color": "#F2495C",
          "stack": "B",
          "yaxis": 2
        }
      ],
      "spaceLength": 10,
      "stack": true,
      "steppedLine": false,
      "targets": [
        {
          "expr": "sum(rate(rollify_notifier_operation_duration_seconds_count{service=\"rollify-server\"}[${interval}])) by (op)",
          "interval": "",
          "legendFormat": "{{op}}",
          "refId": "A"
        },
        {
          "expr": "sum(rate(rollify_notifier_operation_duration_seconds_count{service=\"rollify-server\", success=\"false\"}[${interval}]))\n/\nsum(rate(rollify_notifier_operation_duration_seconds_count{service=\"rollify-server\"}[${interval}]))",
          "interval": "",
          "legendFormat": "error %",
          "refId": "B"
        }
      ],
      "thresholds": [],
      "timeRegions": [],
      "title": "Event publish rate (Notifier)",
      "tooltip": {
        "shared": true,
        "sort": 0,
        "value_type": "individual"
      },
      "type": "graph",
      "xaxis": {
        "mode": "time",
        "show": true,
        "values": []
      },
      "yaxes": [
        {
          "$$hashKey": "object:115",
          "format": "ev/sec",
          "logBase": 1,
          "show": true
        },
        {
          "$$hashKey": "object:116",
          "format": "percentunit",
          "logBase": 1,
          "max": "1",
          "min": "0",
          "show": true
        }
      ],
      "yaxis": {
        "align": false
      }
    },
    {
      "aliasColors": {},
      "bars": false,
      "dashLength": 10,
      "dashes": false,
      "datasource": {
        "type": "prometheus",
        "uid": "P1809F7CD0C75ACF3"
      },
      "description": "Event pusblish latency",
      "fieldConfig": {
        "defaults": {
          "links": []
        },
        "overrides": []
      },
      "fill": 1,
      "fillGradient": 2,
      "gridPos": {
        "h": 8,
        "w": 12,
        "x": 12,
        "y": 22
      },
      "hiddenSeries": false,
      "id": 58,
      "legend": {
        "avg": false,
        "current": false,
        "max": false,
        "min": false,
        "show": true,
        "total": false,
        "values": false
      },
      "lines": true,
      "linewidth": 1,
      "nullPointMode": "null",
      "options": {
        "alertThreshold": true
      },
      "percentage": false,
      "pluginVersion": "8.3.5",
      "pointradius": 2,
      "points": false,
      "renderer": "flot",
      "seriesOverrides": [
        {
          "$$hashKey": "object:185",
          "alias": "p99",
          "color": "#FA6400"
        },
        {
          "$$hashKey": "object:303",
          "alias": "p90",
          "color": "#FFB357"
        },
        {
          "$$hashKey": "object:311",
          "alias": "p50",
          "color": "#FFCB7D"
        }
      ],
      "spaceLength": 10,
      "stack": false,
      "steppedLine": false,
      "targets": [
        {
          "expr": "histogram_quantile(0.99, sum(rate(rollify_notifier_operation_duration_seconds_bucket{service=\"rollify-server\"}[${interval}])) by (le))",
          "interval": "",
          "legendFormat": "p99",
          "refId": "A"
        },
        {
          "expr": "histogram_quantile(0.90, sum(rate(rollify_notifier_operation_duration_seconds_bucket{service=\"rollify-server\"}[${interval}])) by (le))",
          "interval": "",
          "legendFormat": "p90",
          "refId": "B"
        },
        {
          "expr": "histogram_quantile(0.50, sum(rate(rollify_notifier_operation_duration_seconds_bucket{service=\"rollify-server\"}[${interval}])) by (le))",
          "interval": "",
          "legendFormat": "p50",
          "refId": "C"
        }
      ],
      "thresholds": [],
      "timeRegions": [],
      "title": "Event publish latency (Notifier)",
      "tooltip": {
        "shared": true,
        "sort": 0,
        "value_type": "individual"
      },
      "type": "graph",
      "xaxis": {
        "mode": "time",
        "show": true,
        "values": []
      },
      "yaxes": [
        {
          "$$hashKey": "object:115",
          "format": "s",
          "logBase": 1,
          "show": true
        },
        {
          "$$hashKey": "object:116",
          "format": "short",
          "logBase": 1,
          "show": true
        }
      ],
      "yaxis": {
        "align": false
      }
    },
    {
      "aliasColors": {},
      "bars": false,
      "dashLength": 10,
      "dashes": false,
      "datasource": {
        "type": "prometheus",
        "uid": "P1809F7CD0C75ACF3"
      },
      "description": "The rate of events handled by all the subscribers",
      "fieldConfig": {
        "defaults": {
          "links": []
        },
        "overrides": []
      },
      "fill": 1,
      "fillGradient": 2,
      "gridPos": {
        "h": 8,
        "w": 12,
        "x": 0,
        "y": 30
      },
      "hiddenSeries": false,
      "id": 59,
      "legend": {
        "avg": false,
        "current": false,
        "max": false,
        "min": false,
        "show": true,
        "total": false,
        "values": false
      },
      "lines": true,
      "linewidth": 1,
      "nullPointMode": "null",
      "percentage": false,
      "pluginVersion": "8.3.5",
      "pointradius": 2,
      "points": false,
      "renderer": "flot",
      "seriesOverrides": [
        {
          "$$hashKey": "object:185",
          "alias": "error %",
          "color": "#F2495C",
          "stack": "B",
          "yaxis": 2
        }
      ],
      "spaceLength": 10,
      "stack": true,
      "steppedLine": false,
      "targets": [
        {
          "expr": "sum(rate(rollify_subscriber_event_handler_duration_seconds_count{service=\"rollify-server\"}[${interval}])) by (subscription)",
          "interval": "",
          "legendFormat": "{{subscription}}",
          "refId": "A"
        },
        {
          "expr": "sum(rate(rollify_subscriber_event_handler_duration_seconds_count{service=\"rollify-server\", success=\"false\"}[${interval}]))\n/\nsum(rate(rollify_subscriber_event_handler_duration_seconds_count{service=\"rollify-server\"}[${interval}]))",
          "interval": "",
          "legendFormat": "error %",
          "refId": "B"
        }
      ],
      "thresholds": [],
      "timeRegions": [],
      "title": "Event handle rate (Subscriber/consumer)",
      "tooltip": {
        "shared": true,
        "sort": 0,
        "value_type": "individual"
      },
      "type": "graph",
      "xaxis": {
        "mode": "time",
        "show": true,
        "values": []
      },
      "yaxes": [
        {
          "$$hashKey": "object:115",
          "format": "ev/sec",
          "logBase": 1,
          "show": true
        },
        {
          "$$hashKey": "object:116",
          "format": "percentunit",
          "logBase": 1,
          "max": "1",
          "min": "0",
          "show": true
        }
      ],
      "yaxis": {
        "align": false
      }
    },
    {
      "aliasColors": {},
      "bars": false,
      "dashLength": 10,
      "dashes": false,
      "datasource": {
        "type": "prometheus",
        "uid": "P1809F7CD0C75ACF3"
      },
      "description": "Event handle latency by all the subscribers",
      "fieldConfig": {
        "defaults": {
          "links": []
        },
        "overrides": []
      },
      "fill": 1,
      "fillGradient": 2,
      "gridPos": {
        "h": 8,
        "w": 12,
        "x": 12,
        "y": 30
      },
      "hiddenSeries": false,
      "id": 60,
      "legend": {
        "avg": false,
        "current": false,
        "max": false,
        "min": false,
        "show": true,
        "total": false,
        "values": false
      },
      "lines": true,
      "linewidth": 1,
      "nullPointMode": "null",
      "percentage": false,
      "pluginVersion": "8.3.5",
      "pointradius": 2,
      "points": false,
      "renderer": "flot",
      "seriesOverrides": [
        {
          "$$hashKey": "object:185",
          "alias": "p99",
          "color": "#FA6400"
        },
        {
          "$$hashKey": "object:303",
          "alias": "p90",
          "color": "#FFB357"
        },
        {
          "$$hashKey": "object:311",
          "alias": "p50",
          "color": "#FFCB7D"
        }
      ],
      "spaceLength": 10,
      "stack": false,
      "steppedLine": false,
      "targets": [
        {
          "expr": "histogram_quantile(0.99, sum(rate(rollify_subscriber_event_handler_duration_seconds_bucket{service=\"rollify-server\"}[${interval}])) by (le))",
          "interval": "",
          "legendFormat": "p99",
          "refId": "A"
        },
        {
          "expr": "histogram_quantile(0.90, sum(rate(rollify_subscriber_event_handler_duration_seconds_bucket{service=\"rollify-server\"}[${interval}])) by (le))",
          "interval": "",
          "legendFormat": "p90",
          "refId": "B"
        },
        {
          "expr": "histogram_quantile(0.50, sum(rate(rollify_subscriber_event_handler_duration_seconds_bucket{service=\"rollify-server\"}[${interval}])) by (le))",
          "interval": "",
          "legendFormat": "p50",
          "refId": "C"
        }
      ],
      "thresholds": [],
      "timeRegions": [],
      "title": "Event handle latency (Subscriber/consumer)",
      "tooltip": {
        "shared": true,
        "sort": 0,
        "value_type": "individual"
      },
      "type": "graph",
      "xaxis": {
        "mode": "time",
        "show": true,
        "values": []
      },
      "yaxes": [
        {
          "$$hashKey": "object:115",
          "format": "s",
          "logBase": 1,
          "show": true
        },
        {
          "$$hashKey": "object:116",
          "format": "short",
          "logBase": 1,
          "show": true
        }
      ],
      "yaxis": {
        "align": false
      }
    },
    {
      "collapsed": false,
      "gridPos": {
        "h": 1,
        "w": 24,
        "x": 0,
        "y": 38
      },
      "id": 33,
      "panels": [],
      "title": "Storage",
      "type": "row"
    },
    {
      "datasource": {
        "type": "prometheus",
        "uid": "P1809F7CD0C75ACF3"
      },
      "description": "The OPS data by opration",
      "fieldConfig": {
        "defaults": {
          "custom": {
            "align": "left",
            "displayMode": "auto"
          },
          "mappings": [],
          "thresholds": {
            "mode": "absolute",
            "steps": [
              {
                "color": "green",
                "value": null
              }
            ]
          }
        },
        "overrides": [
          {
            "matcher": {
              "id": "byName",
              "options": "Value"
            },
            "properties": [
              {
                "id": "unit",
                "value": "ops"
              },
              {
                "id": "displayName",
                "value": "Reqps"
              }
            ]
          }
        ]
      },
      "gridPos": {
        "h": 5,
        "w": 12,
        "x": 0,
        "y": 39
      },
      "id": 71,
      "options": {
        "footer": {
          "fields": "",
          "reducer": [
            "sum"
          ],
          "show": false
        },
        "showHeader": true
      },
      "pluginVersion": "8.3.5",
      "targets": [
        {
          "expr": "sum(rate(rollify_dice_roll_repository_operation_duration_seconds_count{service=\"rollify-server\"}[${interval}])) by (success, op)",
          "format": "table",
          "instant": true,
          "interval": "",
          "legendFormat": "",
          "refId": "A"
        }
      ],
      "title": "Repository Ops rate",
      "transformations": [
        {
          "id": "filterFieldsByName",
          "options": {
            "include": {
              "names": [
                "Value",
                "success",
                "op"
              ]
            }
          }
        }
      ],
      "type": "table"
    },
    {
      "datasource": {
        "type": "prometheus",
        "uid": "P1809F7CD0C75ACF3"
      },
      "description": "The repository latency data by operation",
      "fieldConfig": {
        "defaults": {
          "custom": {
            "align": "left",
            "displayMode": "auto"
          },
          "mappings": [],
          "thresholds": {
            "mode": "absolute",
            "steps": [
              {
                "color": "green",
                "value": null
              }
            ]
          }
        },
        "overrides": [
          {
            "matcher": {
              "id": "byName",
              "options": "Value"
            },
            "properties": [
              {
                "id": "unit",
                "value": "ms"
              },
              {
                "id": "displayName",
                "value": "Latency"
              },
              {
                "id": "thresholds",
                "value": {
                  "mode": "absolute",
                  "steps": [
                    {
                      "color": "green",
                      "value": null
                    },
                    {
                      "color": "orange",
                      "value": 500
                    },
                    {
                      "color": "red",
                      "value": 1000
                    }
                  ]
                }
              },
              {
                "id": "custom.displayMode",
                "value": "color-text"
              }
            ]
          }
        ]
      },
      "gridPos": {
        "h": 5,
        "w": 12,
        "x": 12,
        "y": 39
      },
      "id": 72,
      "options": {
        "footer": {
          "fields": "",
          "reducer": [
            "sum"
          ],
          "show": false
        },
        "showHeader": true
      },
      "pluginVersion": "8.3.5",
      "targets": [
        {
          "expr": "(histogram_quantile(0.99, sum(rate(rollify_dice_roll_repository_operation_duration_seconds_bucket[${interval}])) by (le, op, success)) > 0) * 1000",
          "format": "table",
          "instant": true,
          "interval": "",
          "legendFormat": "",
          "refId": "A"
        }
      ],
      "title": "Repository latency by operation",
      "transformations": [
        {
          "id": "filterFieldsByName",
          "options": {
            "include": {
              "names": [
                "success",
                "Value",
                "op"
              ]
            }
          }
        }
      ],
      "type": "table"
    },
    {
      "aliasColors": {},
      "bars": false,
      "dashLength": 10,
      "dashes": false,
      "datasource": {
        "type": "prometheus",
        "uid": "P1809F7CD0C75ACF3"
      },
      "description": "repository operation rate",
      "fieldConfig": {
        "defaults": {
          "links": []
        },
        "overrides": []
      },
      "fill": 1,
      "fillGradient": 2,
      "gridPos": {
        "h": 8,
        "w": 12,
        "x": 0,
        "y": 44
      },
      "hiddenSeries": false,
      "id": 34,
      "legend": {
        "avg": false,
        "current": false,
        "max": false,
        "min": false,
        "show": true,
        "total": false,
        "values": false
      },
      "lines": true,
      "linewidth": 1,
      "nullPointMode": "null",
      "percentage": false,
      "pluginVersion": "8.3.5",
      "pointradius": 2,
      "points": false,
      "renderer": "flot",
      "seriesOverrides": [
        {
          "$$hashKey": "object:185",
          "alias": "error %",
          "color": "#F2495C",
          "stack": "B",
          "yaxis": 2
        }
      ],
      "spaceLength": 10,
      "stack": true,
      "steppedLine": false,
      "targets": [
        {
          "expr": "sum(rate(rollify_dice_roll_repository_operation_duration_seconds_count{service=\"rollify-server\"}[${interval}])) by (op)",
          "interval": "",
          "legendFormat": "{{op}}",
          "refId": "A"
        },
        {
          "expr": "sum(rate(rollify_dice_roll_repository_operation_duration_seconds_count{service=\"rollify-server\", success=\"false\"}[${interval}]))\n/\nsum(rate(rollify_dice_roll_repository_operation_duration_seconds_count{service=\"rollify-server\"}[${interval}]))",
          "interval": "",
          "legendFormat": "error %",
          "refId": "B"
        }
      ],
      "thresholds": [],
      "timeRegions": [],
      "title": "Repository operation rate",
      "tooltip": {
        "shared": true,
        "sort": 0,
        "value_type": "individual"
      },
      "type": "graph",
      "xaxis": {
        "mode": "time",
        "show": true,
        "values": []
      },
      "yaxes": [
        {
          "$$hashKey": "object:115",
          "format": "reqps",
          "logBase": 1,
          "show": true
        },
        {
          "$$hashKey": "object:116",
          "format": "percentunit",
          "logBase": 1,
          "max": "1",
          "min": "0",
          "show": true
        }
      ],
      "yaxis": {
        "align": false
      }
    },
    {
      "aliasColors": {},
      "bars": false,
      "dashLength": 10,
      "dashes": false,
      "datasource": {
        "type": "prometheus",
        "uid": "P1809F7CD0C75ACF3"
      },
      "description": "Repository  operation latency",
      "fieldConfig": {
        "defaults": {
          "links": []
        },
        "overrides": []
      },
      "fill": 1,
      "fillGradient": 2,
      "gridPos": {
        "h": 8,
        "w": 12,
        "x": 12,
        "y": 44
      },
      "hiddenSeries": false,
      "id": 35,
      "legend": {
        "avg": false,
        "current": false,
        "max": false,
        "min": false,
        "show": true,
        "total": false,
        "values": false
      },
      "lines": true,
      "linewidth": 1,
      "nullPointMode": "null",
      "percentage": false,
      "pluginVersion": "8.3.5",
      "pointradius": 2,
      "points": false,
      "renderer": "flot",
      "seriesOverrides": [
        {
          "$$hashKey": "object:185",
          "alias": "p99",
          "color": "#FA6400"
        },
        {
          "$$hashKey": "object:303",
          "alias": "p90",
          "color": "#FFB357"
        },
        {
          "$$hashKey": "object:311",
          "alias": "p50",
          "color": "#FFCB7D"
        }
      ],
      "spaceLength": 10,
      "stack": false,
      "steppedLine": false,
      "targets": [
        {
          "expr": "histogram_quantile(0.99, sum(rate(rollify_dice_roll_repository_operation_duration_seconds_bucket[${interval}])) by (le))",
          "interval": "",
          "legendFormat": "p99",
          "refId": "A"
        },
        {
          "expr": "histogram_quantile(0.90, sum(rate(rollify_dice_roll_repository_operation_duration_seconds_bucket[${interval}])) by (le))",
          "interval": "",
          "legendFormat": "p90",
          "refId": "B"
        },
        {
          "expr": "histogram_quantile(0.50, sum(rate(rollify_dice_roll_repository_operation_duration_seconds_bucket[${interval}])) by (le))",
          "interval": "",
          "legendFormat": "p50",
          "refId": "C"
        }
      ],
      "thresholds": [],
      "timeRegions": [],
      "title": "Repository latency",
      "tooltip": {
        "shared": true,
        "sort": 0,
        "value_type": "individual"
      },
      "type": "graph",
      "xaxis": {
        "mode": "time",
        "show": true,
        "values": []
      },
      "yaxes": [
        {
          "$$hashKey": "object:115",
          "format": "s",
          "logBase": 1,
          "show": true
        },
        {
          "$$hashKey": "object:116",
          "format": "short",
          "logBase": 1,
          "show": true
        }
      ],
      "yaxis": {
        "align": false
      }
    },
    {
      "collapsed": false,
      "gridPos": {
        "h": 1,
        "w": 24,
        "x": 0,
        "y": 52
      },
      "id": 11,
      "panels": [],
      "title": "Dice rolls",
      "type": "row"
    },
    {
      "aliasColors": {},
      "bars": false,
      "dashLength": 10,
      "dashes": false,
      "datasource": {
        "type": "prometheus",
        "uid": "P1809F7CD0C75ACF3"
      },
      "description": "The rate of rolled dice",
      "fieldConfig": {
        "defaults": {
          "links": []
        },
        "overrides": []
      },
      "fill": 1,
      "fillGradient": 0,
      "gridPos": {
        "h": 8,
        "w": 12,
        "x": 0,
        "y": 53
      },
      "hiddenSeries": false,
      "id": 2,
      "legend": {
        "avg": false,
        "current": false,
        "max": false,
        "min": false,
        "show": true,
        "total": false,
        "values": false
      },
      "lines": true,
      "linewidth": 1,
      "nullPointMode": "null",
      "percentage": false,
      "pluginVersion": "8.3.5",
      "pointradius": 2,
      "points": false,
      "renderer": "flot",
      "seriesOverrides": [],
      "spaceLength": 10,
      "stack": true,
      "steppedLine": false,
      "targets": [
        {
          "expr": "sum(rate(rollify_dice_roller_die_roll_results_total{service=\"rollify-server\"}[${interval}])) by (die_type) ",
          "interval": "",
          "legendFormat": "{{die_type}}",
          "refId": "A"
        }
      ],
      "thresholds": [],
      "timeRegions": [],
      "title": "Dice roll rate",
      "tooltip": {
        "shared": true,
        "sort": 0,
        "value_type": "individual"
      },
      "type": "graph",
      "xaxis": {
        "mode": "time",
        "show": true,
        "values": []
      },
      "yaxes": [
        {
          "$$hashKey": "object:106",
          "format": "short",
          "logBase": 1,
          "show": true
        },
        {
          "$$hashKey": "object:107",
          "format": "short",
          "logBase": 1,
          "show": true
        }
      ],
      "yaxis": {
        "align": false
      }
    },
    {
      "aliasColors": {},
      "bars": false,
      "dashLength": 10,
      "dashes": false,
      "datasource": {
        "type": "prometheus",
        "uid": "P1809F7CD0C75ACF3"
      },
      "description": "These are the percentiles of the quantity of the dice rolls. e.g p99, means that the 99% of the dice rolls have N dice quantity per dice roll or less.",
      "fieldConfig": {
        "defaults": {
          "links": []
        },
        "overrides": []
      },
      "fill": 1,
      "fillGradient": 2,
      "gridPos": {
        "h": 8,
        "w": 12,
        "x": 12,
        "y": 53
      },
      "hiddenSeries": false,
      "id": 36,
      "legend": {
        "avg": false,
        "current": false,
        "max": false,
        "min": false,
        "show": true,
        "total": false,
        "values": false
      },
      "lines": false,
      "linewidth": 1,
      "nullPointMode": "null",
      "percentage": false,
      "pluginVersion": "8.3.5",
      "pointradius": 2,
      "points": true,
      "renderer": "flot",
      "seriesOverrides": [
        {
          "$$hashKey": "object:185",
          "alias": "p99",
          "color": "#8F3BB8"
        },
        {
          "$$hashKey": "object:303",
          "alias": "p90",
          "color": "#CA95E5"
        },
        {
          "$$hashKey": "object:311",
          "alias": "p50",
          "color": "#DEB6F2"
        }
      ],
      "spaceLength": 10,
      "stack": false,
      "steppedLine": false,
      "targets": [
        {
          "expr": "histogram_quantile(0.99, sum(rate(rollify_dice_roller_dice_roll_die_quantity_bucket{service=\"rollify-server\"}[${interval}])) by (le))",
          "interval": "",
          "legendFormat": "p99",
          "refId": "A"
        },
        {
          "expr": "histogram_quantile(0.90, sum(rate(rollify_dice_roller_dice_roll_die_quantity_bucket[${interval}])) by (le))",
          "interval": "",
          "legendFormat": "p90",
          "refId": "B"
        },
        {
          "expr": "histogram_quantile(0.50, sum(rate(rollify_dice_roller_dice_roll_die_quantity_bucket[${interval}])) by (le))",
          "interval": "",
          "legendFormat": "p50",
          "refId": "C"
        }
      ],
      "thresholds": [],
      "timeRegions": [],
      "title": "Dice quantity dice roll",
      "tooltip": {
        "shared": true,
        "sort": 0,
        "value_type": "individual"
      },
      "type": "graph",
      "xaxis": {
        "mode": "time",
        "show": true,
        "values": []
      },
      "yaxes": [
        {
          "$$hashKey": "object:115",
          "format": "dice",
          "logBase": 1,
          "show": true
        },
        {
          "$$hashKey": "object:116",
          "format": "short",
          "logBase": 1,
          "show": true
        }
      ],
      "yaxis": {
        "align": false
      }
    },
    {
      "datasource": {
        "type": "prometheus",
        "uid": "P1809F7CD0C75ACF3"
      },
      "description": "The % of dice roll results by result value",
      "fieldConfig": {
        "defaults": {
          "decimals": 3,
          "mappings": [],
          "max": 1,
          "min": 0,
          "thresholds": {
            "mode": "absolute",
            "steps": [
              {
                "color": "semi-dark-purple",
                "value": null
              }
            ]
          },
          "unit": "percentunit"
        },
        "overrides": []
      },
      "gridPos": {
        "h": 11,
        "w": 6,
        "x": 0,
        "y": 61
      },
      "id": 4,
      "maxPerRow": 4,
      "options": {
        "displayMode": "gradient",
        "orientation": "horizontal",
        "reduceOptions": {
          "calcs": [
            "last"
          ],
          "fields": "",
          "values": false
        },
        "showUnfilled": true
      },
      "pluginVersion": "8.3.5",
      "repeat": "die_type",
      "repeatDirection": "h",
      "targets": [
        {
          "expr": "sum(increase(rollify_dice_roller_die_roll_results_total{service=\"rollify-server\", die_type=\"${die_type}\"}[24h])) by (die_type, die_side) \n  /on(die_type) group_left \nsum(increase(rollify_dice_roller_die_roll_results_total{service=\"rollify-server\",die_type=\"${die_type}\"}[24h]))  by (die_type)\n",
          "instant": true,
          "interval": "",
          "legendFormat": "{{die_side}}",
          "refId": "A"
        }
      ],
      "title": "Dice buckets by value (${die_type})",
      "type": "bargauge"
    }
  ],
  "refresh": "1m",
  "schemaVersion": 34,
  "style": "dark",
  "tags": [
      "rollify",
      "slok"
  ],
  "templating": {
    "list": [
      {
        "auto": true,
        "auto_count": "50",
        "auto_min": "1m",
        "current": {
          "selected": false,
          "text": "auto",
          "value": "$__auto_interval_interval"
        },
        "hide": 2,
        "name": "interval",
        "options": [
          {
            "selected": true,
            "text": "auto",
            "value": "$__auto_interval_interval"
          },
          {
            "selected": false,
            "text": "1m",
            "value": "1m"
          }
        ],
        "query": "1m",
        "refresh": 2,
        "skipUrlSync": false,
        "type": "interval"
      },
      {
        "current": {
          "selected": true,
          "text": [
            "All"
          ],
          "value": [
            "$__all"
          ]
        },
        "datasource": {
          "type": "prometheus",
          "uid": "P1809F7CD0C75ACF3"
        },
        "definition": "label_values(rollify_dice_roller_die_roll_results_total, die_type)",
        "hide": 0,
        "includeAll": true,
        "label": "Die type",
        "multi": true,
        "name": "die_type",
        "options": [],
        "query": {
          "query": "label_values(rollify_dice_roller_die_roll_results_total, die_type)",
          "refId": "prometheus-die_type-Variable-Query"
        },
        "refresh": 2,
        "regex": "",
        "skipUrlSync": false,
        "sort": 0,
        "tagValuesQuery": "",
        "tagsQuery": "",
        "type": "query",
        "useTags": false
      }
    ]
  },
  "time": {
    "from": "now-30m",
    "to": "now"
  },
  "timepicker": {
    "refresh_intervals": [
      "10s",
      "30s",
      "1m",
      "5m",
      "15m",
      "30m",
      "1h",
      "2h",
      "1d"
    ]
  },
  "timezone": "",
  "title": "Rollify",
  "uid": "rollify",
  "version": 1,
  "weekStart": ""
}